LICENSE
wagtail_typograf/__init__.py
wagtail_typograf/handlers.py
wagtail_typograf/static/wagtail_typograf/js/typograf.js
wagtail_typograf/urls.py
wagtail_typograf/views.py
wagtail_typograf/wagtail_hooks.py
wagtail_typograf-0.1.3.dist-info/LICENSE
wagtail_typograf-0.1.3.dist-info/WHEEL
wagtail_typograf-0.1.3.dist-info/METADATA
wagtail_typograf-0.1.3.dist-info/RECORD
