Metadata-Version: 2.1
Name: wagtail-typograf
Version: 0.1.3
Summary: Brings russian typography to Wagtail rich text editor based on draftail
Home-page: https://github.com/truetug/wagtail-typograf
License: MIT
Keywords: wagtail,draftail,typography,typus
Author: Sergey Trofimov
Author-email: truetug@gmail.com
Requires-Python: >=3.3,<4.0
Classifier: License :: OSI Approved :: MIT License
Classifier: Operating System :: OS Independent
Classifier: Programming Language :: Python :: 3
Classifier: Programming Language :: Python :: 3.10
Classifier: Programming Language :: Python :: 3.4
Classifier: Programming Language :: Python :: 3.5
Classifier: Programming Language :: Python :: 3.6
Classifier: Programming Language :: Python :: 3.7
Classifier: Programming Language :: Python :: 3.8
Classifier: Programming Language :: Python :: 3.9
Classifier: Topic :: Text Editors
Classifier: Topic :: Text Editors :: Text Processing
Requires-Dist: typus (>=0.2.2,<0.3.0)
Project-URL: Repository, https://github.com/truetug/wagtail-typograf
